testcontainers/core/__init__.py
testcontainers/core/config.py
testcontainers/core/container.py
testcontainers/core/docker_client.py
testcontainers/core/exceptions.py
testcontainers/core/generic.py
testcontainers/core/utils.py
testcontainers/core/waiting_utils.py
tests/test_core.py
tests/test_docker_client.py
tests/test_docker_in_docker.py
tests/test_new_docker_api.py
testcontainers_core-0.0.1rc1.dist-info/METADATA
testcontainers_core-0.0.1rc1.dist-info/WHEEL
testcontainers_core-0.0.1rc1.dist-info/top_level.txt
testcontainers_core-0.0.1rc1.dist-info/RECORD
