Metadata-Version: 2.1
Name: testcontainers-core
Version: 0.0.1rc1
Summary: Core component of testcontainers-python.
Home-page: https://github.com/testcontainers/testcontainers-python
Requires-Python: >=3.7
Requires-Dist: docker (>=4.0.0)
Requires-Dist: wrapt
